dart_trec_learner/__init__.py
dart_trec_learner/app_config.py
dart_trec_learner/learner.py
dart_trec_learner/predictor.py
dart_trec_learner/preprocessor.py
dart_trec_learner/validator.py
dart_trec_learner/utils/__init__.py
dart_trec_learner/utils/confusion_matrix.py
dart_trec_learner/utils/parse.py
utils/__init__.py
utils/singleton.py
dart_trec_learner-3.1.0.dist-info/LICENSE
dart_trec_learner-3.1.0.dist-info/METADATA
dart_trec_learner-3.1.0.dist-info/WHEEL
dart_trec_learner-3.1.0.dist-info/dependency_links.txt
dart_trec_learner-3.1.0.dist-info/top_level.txt
dart_trec_learner-3.1.0.dist-info/RECORD
