Metadata-Version: 2.1
Name: dart-trec-learner
Version: 3.1.0
Summary: T-REC learner libs
Home-page: https://github.sec.samsung.net/SOL/dart-trec-learner
Author: SIDIA
Author-email: sidia@sidia.com
License: UNKNOWN
Platform: UNKNOWN
Classifier: Programming Language :: Python :: 3
Classifier: License :: OSI Approved :: Apache Software License
Classifier: Operating System :: OS Independent
Requires-Python: ~=3.7
License-File: LICENSE
Requires-Dist: accelerate (==1.1.0)
Requires-Dist: apscheduler (==3.10.1)
Requires-Dist: boto3 (==1.34.0)
Requires-Dist: dart-trec-commons (==2.8.3)
Requires-Dist: datasets (==3.1.0)
Requires-Dist: diffusers (==0.31.0)
Requires-Dist: evaluate (==0.4.3)
Requires-Dist: isort (==5.13.2)
Requires-Dist: loguru (==0.7.2)
Requires-Dist: pynvml (==11.5.3)
Requires-Dist: python-dotenv (==1.0.1)
Requires-Dist: scikit-learn (==1.5.2)
Requires-Dist: tabulate (==0.9.0)
Requires-Dist: torch (==2.3.0)
Requires-Dist: torchvision (==0.18.0)
Requires-Dist: tqdm (==4.67.0)
Requires-Dist: transformers (==4.46.3)
Requires-Dist: typer (==0.13.0)
Requires-Dist: tzlocal (==2.1)
